epub_extract_links/__init__.py
epub_extract_links/__main__.py
epub_extract_links-0.1.1.dist-info/LICENSE
epub_extract_links-0.1.1.dist-info/METADATA
epub_extract_links-0.1.1.dist-info/WHEEL
epub_extract_links-0.1.1.dist-info/entry_points.txt
epub_extract_links-0.1.1.dist-info/top_level.txt
epub_extract_links-0.1.1.dist-info/RECORD
