Metadata-Version: 2.1
Name: epub-extract-links
Version: 0.1.1
Summary: Extract web links from EPUB files
Home-page: https://github.com/dolugen/epub-extract-links
Author: Dulguun Battulga
Project-URL: Bug Tracker, https://github.com/dolugen/epub-extract-links/issues
Classifier: Programming Language :: Python :: 3
Classifier: License :: OSI Approved :: MIT License
Classifier: Operating System :: OS Independent
Requires-Python: >=3.7
License-File: LICENSE
Requires-Dist: beautifulsoup4
Requires-Dist: lxml
